gevent_socketio-0.3.6.dist-info/METADATA
gevent_socketio-0.3.6.dist-info/entry_points.txt
gevent_socketio-0.3.6.dist-info/pydist.json
gevent_socketio-0.3.6.dist-info/DESCRIPTION.rst
gevent_socketio-0.3.6.dist-info/RECORD
gevent_socketio-0.3.6.dist-info/WHEEL
gevent_socketio-0.3.6.dist-info/top_level.txt
socketio/mixins.py
socketio/sgunicorn.py
socketio/server.py
socketio/handler.py
socketio/policyserver.py
socketio/defaultjson.py
socketio/packet.py
socketio/transports.py
socketio/namespace.py
socketio/virtsocket.py
socketio/__init__.py
socketio/sdjango.py
